coregtor/__init__.py
coregtor/clusters.py
coregtor/config.py
coregtor/context.py
coregtor/dataset.py
coregtor/forest.py
coregtor/utils/__init__.py
coregtor/utils/exp.py
coregtor/utils/plot.py
coregtor/utils/validation.py
coregtor/validation/__init__.py
coregtor/validation/ppi.py
coregtor/validation/trdb.py
coregtor-0.1.8.dist-info/METADATA
coregtor-0.1.8.dist-info/WHEEL
coregtor-0.1.8.dist-info/licenses/LICENSE
coregtor-0.1.8.dist-info/RECORD
