Metadata-Version: 2.4
Name: coregtor
Version: 0.1.8
Summary: A tool to predict transcription co-regulators for a gene from gene expression data using random forest methods
License-Expression: MIT
License-File: LICENSE
Author: Shubh Vardhan Jain
Author-email: shubhvjain@gmail.com
Requires-Python: >=3.11
Classifier: Programming Language :: Python :: 3
Classifier: Programming Language :: Python :: 3.11
Classifier: Programming Language :: Python :: 3.12
Classifier: Programming Language :: Python :: 3.13
Classifier: Programming Language :: Python :: 3.14
Requires-Dist: decoupler (>=2.1.1,<3.0.0)
Requires-Dist: matplotlib (>=3.10.7,<4.0.0)
Requires-Dist: networkx (>=3.5,<4.0)
Requires-Dist: numpy (>=2.3.4,<3.0.0)
Requires-Dist: pandas (>=2.3.3,<3.0.0)
Requires-Dist: scikit-learn (>=1.7.2,<2.0.0)
Requires-Dist: seaborn (>=0.13.2,<0.14.0)
